NLPPlus/bindings.cp311-win_amd64.pyd
NLPPlus/_version.py
NLPPlus/__init__.py
NLPPlus/analyzers/address-parser/README.md
NLPPlus/analyzers/address-parser/input/text.txt
NLPPlus/analyzers/address-parser/kb/user/address-synonym.dict
NLPPlus/analyzers/address-parser/kb/user/attr.kb
NLPPlus/analyzers/address-parser/kb/user/Country.dict
NLPPlus/analyzers/address-parser/kb/user/designator.dict
NLPPlus/analyzers/address-parser/kb/user/directions.dict
NLPPlus/analyzers/address-parser/kb/user/en-usa-states.dict
NLPPlus/analyzers/address-parser/kb/user/en-usa-streetsuff.dict
NLPPlus/analyzers/address-parser/kb/user/hier.kb
NLPPlus/analyzers/address-parser/kb/user/military-address.dict
NLPPlus/analyzers/address-parser/kb/user/phr.kb
NLPPlus/analyzers/address-parser/kb/user/word.kb
NLPPlus/analyzers/address-parser/spec/analyzer.seq
NLPPlus/analyzers/address-parser/spec/Changenumbers.nlp
NLPPlus/analyzers/address-parser/spec/countryname.nlp
NLPPlus/analyzers/address-parser/spec/funcs.nlp
NLPPlus/analyzers/address-parser/spec/Grouping.nlp
NLPPlus/analyzers/address-parser/spec/information.nlp
NLPPlus/analyzers/address-parser/spec/information1.nlp
NLPPlus/analyzers/address-parser/spec/information2.nlp
NLPPlus/analyzers/address-parser/spec/information3.nlp
NLPPlus/analyzers/address-parser/spec/kbdisp01.nlp
NLPPlus/analyzers/address-parser/spec/KBFuncs.nlp
NLPPlus/analyzers/address-parser/spec/kbinit.nlp
NLPPlus/analyzers/address-parser/spec/kbmake.nlp
NLPPlus/analyzers/address-parser/spec/Lines.nlp
NLPPlus/analyzers/address-parser/spec/output.nlp
NLPPlus/analyzers/address-parser/spec/pincode.nlp
NLPPlus/analyzers/address-parser/spec/PrecedingWords.nlp
NLPPlus/analyzers/address-parser/spec/removelines.nlp
NLPPlus/analyzers/address-parser/spec/RemovePunct.nlp
NLPPlus/analyzers/address-parser/spec/RemoveSpecialChars.nlp
NLPPlus/analyzers/address-parser/spec/RemoveWhiteSpace.nlp
NLPPlus/analyzers/address-parser/tmp/README.md
NLPPlus/analyzers/emailaddress/README.md
nlpplus-1.0.5.dist-info/DELVEWHEEL
nlpplus-1.0.5.dist-info/METADATA
nlpplus-1.0.5.dist-info/RECORD
nlpplus-1.0.5.dist-info/WHEEL
nlpplus-1.0.5.dist-info/licenses/LICENSE
