Metadata-Version: 2.2
Name: NLPPlus
Version: 1.0.5
Summary: Python extension for the NLP++ text analysis engine
Keywords: nlp,text
Author-Email: David De Hilster <contact@visualtext.org>
License: MIT License
Classifier: Development Status :: 3 - Alpha
Classifier: Intended Audience :: Developers
Classifier: License :: OSI Approved :: MIT License
Classifier: Programming Language :: Python :: 3
Classifier: Programming Language :: Python :: 3.8
Classifier: Programming Language :: Python :: 3.9
Classifier: Programming Language :: Python :: 3.10
Classifier: Programming Language :: Python :: 3.11
Classifier: Programming Language :: Python :: 3.12
Project-URL: Homepage, https://visualtext.org/
Project-URL: Repository, https://github.com/VisualText/py-package-nlpengine
Project-URL: Issues, https://github.com/VisualText/py-package-nlpengine
